volgrids/__init__.py
volgrids/_core/__init__.py
volgrids/_core/grid.py
volgrids/_core/mol_system.py
volgrids/_kernels/__init__.py
volgrids/_kernels/boolean.py
volgrids/_kernels/gaussian.py
volgrids/_kernels/kernel.py
volgrids/_misc/__init__.py
volgrids/_misc/math.py
volgrids/_misc/params_gaussian.py
volgrids/_misc/timer.py
volgrids/_misc/utils.py
volgrids/_parsers/__init__.py
volgrids/_parsers/grid_io.py
volgrids/_parsers/parser_config.py
volgrids/_parsers/parser_ini.py
volgrids/_tables/ligand_example-explained.chem
volgrids/_tables/ligand_example.chem
volgrids/_tables/prot.chem
volgrids/_tables/rna.chem
volgrids/_ui/__init__.py
volgrids/_ui/app.py
volgrids/_ui/param_handler.py
volgrids/smiffer/__init__.py
volgrids/smiffer/_core/__init__.py
volgrids/smiffer/_core/mol_system.py
volgrids/smiffer/_core/trimmer.py
volgrids/smiffer/_parsers/__init__.py
volgrids/smiffer/_parsers/parser_chem_table.py
volgrids/smiffer/_smifs/__init__.py
volgrids/smiffer/_smifs/apbs.py
volgrids/smiffer/_smifs/smif.py
volgrids/smiffer/_smifs/stacking.py
volgrids/smiffer/_smifs/_hbonds/__init__.py
volgrids/smiffer/_smifs/_hbonds/hb.py
volgrids/smiffer/_smifs/_hbonds/hbaccepts.py
volgrids/smiffer/_smifs/_hbonds/hbdonors.py
volgrids/smiffer/_smifs/_hbonds/triplet.py
volgrids/smiffer/_smifs/_hydro/__init__.py
volgrids/smiffer/_smifs/_hydro/hydro.py
volgrids/smiffer/_smifs/_hydro/hydrophilic.py
volgrids/smiffer/_smifs/_hydro/hydrophobic.py
volgrids/smiffer/_ui/__init__.py
volgrids/smiffer/_ui/app.py
volgrids/smiffer/_ui/param_handler.py
volgrids/utils/apbs.sh
volgrids/veins/__init__.py
volgrids/veins/_core/__init__.py
volgrids/veins/_core/grid_ve.py
volgrids/veins/_ui/__init__.py
volgrids/veins/_ui/app.py
volgrids/veins/_ui/param_handler.py
volgrids/vgtools/__init__.py
volgrids/vgtools/_core/__init__.py
volgrids/vgtools/_core/operations.py
volgrids/vgtools/_misc/__init__.py
volgrids/vgtools/_misc/comparison_result.py
volgrids/vgtools/_ui/__init__.py
volgrids/vgtools/_ui/app.py
volgrids-0.2.0.dist-info/licenses/LICENSE.md
volgrids-0.2.0.dist-info/METADATA
volgrids-0.2.0.dist-info/WHEEL
volgrids-0.2.0.dist-info/top_level.txt
volgrids-0.2.0.dist-info/RECORD
