Metadata-Version: 2.4
Name: volgrids
Version: 0.2.0
Summary: Framework for volumetric calculations, with emphasis in biological molecular systems.
Home-page: https://github.com/diegobarmor/volgrids
Author: DiegoBarMor
Author-email: diegobarmor42@gmail.com
License: MIT
Keywords: grid mif smif volumetric molecular structural biology interaction field
Classifier: Programming Language :: Python :: 3
Classifier: License :: OSI Approved :: MIT License
Classifier: Operating System :: OS Independent
Requires-Python: >=3.10
License-File: LICENSE.md
Dynamic: author
Dynamic: author-email
Dynamic: classifier
Dynamic: description
Dynamic: description-content-type
Dynamic: home-page
Dynamic: keywords
Dynamic: license
Dynamic: license-file
Dynamic: requires-python
Dynamic: summary
